{"id":"21400525","date":"2015-01-07","season":2015,"type":"Regular Season","label":"","arena":"","arenaCity":"","attendance":null,"officials":"","home":{"abbr":"WAS","score":101,"q":[30,23,24,24],"fg":0.513,"reb":44,"ast":28,"paint":48,"fast":23},"away":{"abbr":"NYK","score":91,"q":[21,20,26,24],"fg":0.415,"reb":41,"ast":18,"paint":24,"fast":9},"box":{"home":[{"pid":"butlera01","name":"Rasual Butler","min":23,"pts":null,"reb":null,"ast":null,"stl":null,"blk":null,"tov":null,"fgm":null,"fga":null,"tpm":null,"tpa":null,"ftm":null,"fta":null,"pm":null,"start":true},{"pid":"walljo01","name":"John Wall","min":33,"pts":null,"reb":null,"ast":null,"stl":null,"blk":null,"tov":null,"fgm":null,"fga":null,"tpm":null,"tpa":null,"ftm":null,"fta":null,"pm":null,"start":true},{"pid":"blairde01","name":"DeJuan Blair","min":1,"pts":null,"reb":null,"ast":null,"stl":null,"blk":null,"tov":null,"fgm":null,"fga":null,"tpm":null,"tpa":null,"ftm":null,"fta":null,"pm":null,"start":false},{"pid":"templga01","name":"Garrett Temple","min":1,"pts":null,"reb":null,"ast":null,"stl":null,"blk":null,"tov":null,"fgm":null,"fga":null,"tpm":null,"tpa":null,"ftm":null,"fta":null,"pm":null,"start":false},{"pid":null,"name":"Nene Hilario","min":23,"pts":null,"reb":null,"ast":null,"stl":null,"blk":null,"tov":null,"fgm":null,"fga":null,"tpm":null,"tpa":null,"ftm":null,"fta":null,"pm":null,"start":true},{"pid":"millean02","name":"Andre Miller","min":14,"pts":null,"reb":null,"ast":null,"stl":null,"blk":null,"tov":null,"fgm":null,"fga":null,"tpm":null,"tpa":null,"ftm":null,"fta":null,"pm":null,"start":true},{"pid":"serapke01","name":"Kevin Seraphin","min":17,"pts":null,"reb":null,"ast":null,"stl":null,"blk":null,"tov":null,"fgm":null,"fga":null,"tpm":null,"tpa":null,"ftm":null,"fta":null,"pm":null,"start":true},{"pid":"bealbr01","name":"Bradley Beal","min":29,"pts":null,"reb":null,"ast":null,"stl":null,"blk":null,"tov":null,"fgm":null,"fga":null,"tpm":null,"tpa":null,"ftm":null,"fta":null,"pm":null,"start":true},{"pid":"porteot01","name":"Otto Porter Jr.","min":23,"pts":null,"reb":null,"ast":null,"stl":null,"blk":null,"tov":null,"fgm":null,"fga":null,"tpm":null,"tpa":null,"ftm":null,"fta":null,"pm":null,"start":true},{"pid":"humphkr01","name":"Kris Humphries","min":21,"pts":null,"reb":null,"ast":null,"stl":null,"blk":null,"tov":null,"fgm":null,"fga":null,"tpm":null,"tpa":null,"ftm":null,"fta":null,"pm":null,"start":true},{"pid":"goodedr01","name":"Drew Gooden","min":1,"pts":null,"reb":null,"ast":null,"stl":null,"blk":null,"tov":null,"fgm":null,"fga":null,"tpm":null,"tpa":null,"ftm":null,"fta":null,"pm":null,"start":false},{"pid":"gortama01","name":"Marcin Gortat","min":28,"pts":null,"reb":null,"ast":null,"stl":null,"blk":null,"tov":null,"fgm":null,"fga":null,"tpm":null,"tpa":null,"ftm":null,"fta":null,"pm":null,"start":true},{"pid":"webstma02","name":"Martell Webster","min":17,"pts":null,"reb":null,"ast":null,"stl":null,"blk":null,"tov":null,"fgm":null,"fga":null,"tpm":null,"tpa":null,"ftm":null,"fta":null,"pm":null,"start":true}],"away":[{"pid":"prigipa01","name":"Pablo Prigioni","min":20,"pts":null,"reb":null,"ast":null,"stl":null,"blk":null,"tov":null,"fgm":null,"fga":null,"tpm":null,"tpa":null,"ftm":null,"fta":null,"pm":null,"start":true},{"pid":"acyqu01","name":"Quincy Acy","min":29,"pts":null,"reb":null,"ast":null,"stl":null,"blk":null,"tov":null,"fgm":null,"fga":null,"tpm":null,"tpa":null,"ftm":null,"fta":null,"pm":null,"start":true},{"pid":null,"name":"Tim Hardaway Jr.","min":23,"pts":null,"reb":null,"ast":null,"stl":null,"blk":null,"tov":null,"fgm":null,"fga":null,"tpm":null,"tpa":null,"ftm":null,"fta":null,"pm":null,"start":true},{"pid":"weartr01","name":"Travis Wear","min":17,"pts":null,"reb":null,"ast":null,"stl":null,"blk":null,"tov":null,"fgm":null,"fga":null,"tpm":null,"tpa":null,"ftm":null,"fta":null,"pm":null,"start":true},{"pid":"aldrico01","name":"Cole Aldrich","min":31,"pts":null,"reb":null,"ast":null,"stl":null,"blk":null,"tov":null,"fgm":null,"fga":null,"tpm":null,"tpa":null,"ftm":null,"fta":null,"pm":null,"start":true},{"pid":"gallola01","name":"Langston Galloway","min":17,"pts":null,"reb":null,"ast":null,"stl":null,"blk":null,"tov":null,"fgm":null,"fga":null,"tpm":null,"tpa":null,"ftm":null,"fta":null,"pm":null,"start":true},{"pid":"caldejo01","name":"Jose Calderon","min":32,"pts":null,"reb":null,"ast":null,"stl":null,"blk":null,"tov":null,"fgm":null,"fga":null,"tpm":null,"tpa":null,"ftm":null,"fta":null,"pm":null,"start":true},{"pid":"larkish01","name":"Shane Larkin","min":27,"pts":null,"reb":null,"ast":null,"stl":null,"blk":null,"tov":null,"fgm":null,"fga":null,"tpm":null,"tpa":null,"ftm":null,"fta":null,"pm":null,"start":true},{"pid":"bargnan01","name":"Andrea Bargnani","min":null,"pts":null,"reb":null,"ast":null,"stl":null,"blk":null,"tov":null,"fgm":null,"fga":null,"tpm":null,"tpa":null,"ftm":null,"fta":null,"pm":null,"start":false},{"pid":"earlycl01","name":"Cleanthony Early","min":18,"pts":null,"reb":null,"ast":null,"stl":null,"blk":null,"tov":null,"fgm":null,"fga":null,"tpm":null,"tpa":null,"ftm":null,"fta":null,"pm":null,"start":true},{"pid":"smithja02","name":"Jason Smith","min":21,"pts":null,"reb":null,"ast":null,"stl":null,"blk":null,"tov":null,"fgm":null,"fga":null,"tpm":null,"tpa":null,"ftm":null,"fta":null,"pm":null,"start":true}]}}