{"id":"21400060","date":"2014-11-05","season":2015,"type":"Regular Season","label":"","arena":"","arenaCity":"","attendance":null,"officials":"","home":{"abbr":"BKN","score":91,"q":[21,27,18,25],"fg":0.439,"reb":42,"ast":17,"paint":38,"fast":11},"away":{"abbr":"MIN","score":98,"q":[24,23,25,26],"fg":0.411,"reb":51,"ast":22,"paint":36,"fast":14},"box":{"home":[{"pid":"johnsjo02","name":"Joe Johnson","min":30,"pts":22,"reb":3,"ast":2,"stl":0,"blk":0,"tov":3,"fgm":9,"fga":17,"tpm":1,"tpa":4,"ftm":3,"fta":4,"pm":-7,"start":true},{"pid":"willide01","name":"Deron Williams","min":39,"pts":19,"reb":2,"ast":6,"stl":0,"blk":1,"tov":4,"fgm":8,"fga":16,"tpm":3,"tpa":6,"ftm":0,"fta":1,"pm":-18,"start":true},{"pid":"jackja01","name":"Jarrett Jack","min":23,"pts":14,"reb":5,"ast":4,"stl":1,"blk":0,"tov":3,"fgm":5,"fga":8,"tpm":0,"tpa":0,"ftm":4,"fta":4,"pm":5,"start":true},{"pid":"lopezbr01","name":"Brook Lopez","min":33,"pts":10,"reb":5,"ast":0,"stl":2,"blk":2,"tov":4,"fgm":5,"fga":14,"tpm":0,"tpa":0,"ftm":0,"fta":1,"pm":-27,"start":true},{"pid":"bogdabo02","name":"Bojan Bogdanovic","min":22,"pts":9,"reb":2,"ast":0,"stl":1,"blk":0,"tov":0,"fgm":3,"fga":8,"tpm":1,"tpa":4,"ftm":2,"fta":2,"pm":-8,"start":true},{"pid":"teletmi01","name":"Mirza Teletovic","min":20,"pts":9,"reb":6,"ast":0,"stl":0,"blk":1,"tov":1,"fgm":3,"fga":8,"tpm":3,"tpa":7,"ftm":0,"fta":0,"pm":16,"start":true},{"pid":"anderal01","name":"Alan Anderson","min":24,"pts":4,"reb":2,"ast":2,"stl":1,"blk":1,"tov":2,"fgm":1,"fga":1,"tpm":0,"tpa":0,"ftm":2,"fta":3,"pm":5,"start":true},{"pid":"garneke01","name":"Kevin Garnett","min":25,"pts":2,"reb":11,"ast":2,"stl":0,"blk":0,"tov":0,"fgm":1,"fga":7,"tpm":0,"tpa":0,"ftm":0,"fta":0,"pm":-21,"start":true},{"pid":"plumlma01","name":"Mason Plumlee","min":12,"pts":2,"reb":4,"ast":1,"stl":1,"blk":0,"tov":0,"fgm":1,"fga":2,"tpm":0,"tpa":0,"ftm":0,"fta":2,"pm":17,"start":true},{"pid":"kirilan01","name":"Andrei Kirilenko","min":4,"pts":0,"reb":1,"ast":0,"stl":0,"blk":0,"tov":1,"fgm":0,"fga":1,"tpm":0,"tpa":0,"ftm":0,"fta":0,"pm":0,"start":false},{"pid":"jordaje01","name":"Jerome Jordan","min":1,"pts":0,"reb":1,"ast":0,"stl":0,"blk":0,"tov":0,"fgm":0,"fga":0,"tpm":0,"tpa":0,"ftm":0,"fta":0,"pm":3,"start":false},{"pid":"gutiejo01","name":"Jorge Gutierrez","min":null,"pts":0,"reb":0,"ast":0,"stl":0,"blk":0,"tov":0,"fgm":0,"fga":0,"tpm":0,"tpa":0,"ftm":0,"fta":0,"pm":0,"start":false},{"pid":"karasse01","name":"Sergey Karasev","min":null,"pts":0,"reb":0,"ast":0,"stl":0,"blk":0,"tov":0,"fgm":0,"fga":0,"tpm":0,"tpa":0,"ftm":0,"fta":0,"pm":0,"start":false}],"away":[{"pid":"martike02","name":"Kevin Martin","min":37,"pts":24,"reb":6,"ast":3,"stl":1,"blk":0,"tov":2,"fgm":7,"fga":19,"tpm":4,"tpa":9,"ftm":6,"fta":6,"pm":20,"start":true},{"pid":"wiggian01","name":"Andrew Wiggins","min":37,"pts":17,"reb":4,"ast":1,"stl":1,"blk":0,"tov":1,"fgm":7,"fga":12,"tpm":1,"tpa":1,"ftm":2,"fta":4,"pm":23,"start":true},{"pid":"pekovni01","name":"Nikola Pekovic","min":32,"pts":16,"reb":11,"ast":3,"stl":1,"blk":0,"tov":1,"fgm":5,"fga":12,"tpm":0,"tpa":0,"ftm":6,"fta":7,"pm":34,"start":true},{"pid":"rubiori01","name":"Ricky Rubio","min":34,"pts":14,"reb":8,"ast":12,"stl":2,"blk":0,"tov":3,"fgm":6,"fga":11,"tpm":1,"tpa":3,"ftm":1,"fta":2,"pm":26,"start":true},{"pid":"youngth01","name":"Thaddeus Young","min":36,"pts":12,"reb":12,"ast":0,"stl":3,"blk":2,"tov":2,"fgm":6,"fga":14,"tpm":0,"tpa":0,"ftm":0,"fta":0,"pm":22,"start":true},{"pid":"willima01","name":"Mo Williams","min":16,"pts":5,"reb":0,"ast":2,"stl":1,"blk":0,"tov":2,"fgm":2,"fga":8,"tpm":1,"tpa":4,"ftm":0,"fta":0,"pm":-22,"start":true},{"pid":"muhamsh01","name":"Shabazz Muhammad","min":5,"pts":4,"reb":3,"ast":0,"stl":0,"blk":0,"tov":0,"fgm":2,"fga":3,"tpm":0,"tpa":0,"ftm":0,"fta":0,"pm":-8,"start":true},{"pid":"bennean01","name":"Anthony Bennett","min":11,"pts":4,"reb":1,"ast":1,"stl":0,"blk":0,"tov":0,"fgm":1,"fga":4,"tpm":0,"tpa":0,"ftm":2,"fta":3,"pm":-15,"start":true},{"pid":"dienggo01","name":"Gorgui Dieng","min":15,"pts":2,"reb":5,"ast":0,"stl":0,"blk":2,"tov":0,"fgm":1,"fga":4,"tpm":0,"tpa":0,"ftm":0,"fta":0,"pm":-27,"start":true},{"pid":"hummero01","name":"Robbie Hummel","min":null,"pts":0,"reb":0,"ast":0,"stl":0,"blk":0,"tov":0,"fgm":0,"fga":0,"tpm":0,"tpa":0,"ftm":0,"fta":0,"pm":0,"start":false},{"pid":"breweco01","name":"Corey Brewer","min":12,"pts":0,"reb":1,"ast":0,"stl":0,"blk":0,"tov":0,"fgm":0,"fga":3,"tpm":0,"tpa":0,"ftm":0,"fta":0,"pm":-18,"start":true},{"pid":"budinch01","name":"Chase Budinger","min":null,"pts":0,"reb":0,"ast":0,"stl":0,"blk":0,"tov":0,"fgm":0,"fga":0,"tpm":0,"tpa":0,"ftm":0,"fta":0,"pm":0,"start":false},{"pid":"lavinza01","name":"Zach LaVine","min":null,"pts":0,"reb":0,"ast":0,"stl":0,"blk":0,"tov":0,"fgm":0,"fga":0,"tpm":0,"tpa":0,"ftm":0,"fta":0,"pm":0,"start":false}]}}