{"id":"22200523","date":"2022-12-29","season":2023,"type":"Regular Season","label":"","arena":"","arenaCity":"","attendance":null,"officials":"","home":{"abbr":"CHA","score":121,"q":[36,21,28,36],"fg":0.548,"reb":52,"ast":33,"paint":66,"fast":15},"away":{"abbr":"OKC","score":113,"q":[30,30,24,29],"fg":0.424,"reb":41,"ast":15,"paint":56,"fast":6},"box":{"home":[{"pid":"washipj01","name":"P.J. Washington","min":31,"pts":null,"reb":null,"ast":null,"stl":null,"blk":null,"tov":null,"fgm":null,"fga":null,"tpm":null,"tpa":null,"ftm":null,"fta":null,"pm":null,"start":true},{"pid":"oubreke01","name":"Kelly Oubre Jr.","min":13,"pts":null,"reb":null,"ast":null,"stl":null,"blk":null,"tov":null,"fgm":null,"fga":null,"tpm":null,"tpa":null,"ftm":null,"fta":null,"pm":null,"start":false},{"pid":"willima07","name":"Mark Williams","min":21,"pts":null,"reb":null,"ast":null,"stl":null,"blk":null,"tov":null,"fgm":null,"fga":null,"tpm":null,"tpa":null,"ftm":null,"fta":null,"pm":null,"start":false},{"pid":"richani01","name":"Nick Richards","min":null,"pts":null,"reb":null,"ast":null,"stl":null,"blk":null,"tov":null,"fgm":null,"fga":null,"tpm":null,"tpa":null,"ftm":null,"fta":null,"pm":null,"start":false},{"pid":"thorjt01","name":"JT Thor","min":7,"pts":null,"reb":null,"ast":null,"stl":null,"blk":null,"tov":null,"fgm":null,"fga":null,"tpm":null,"tpa":null,"ftm":null,"fta":null,"pm":null,"start":false},{"pid":"roziete01","name":"Terry Rozier","min":33,"pts":null,"reb":null,"ast":null,"stl":null,"blk":null,"tov":null,"fgm":null,"fga":null,"tpm":null,"tpa":null,"ftm":null,"fta":null,"pm":null,"start":true},{"pid":"joneska01","name":"Kai Jones","min":null,"pts":null,"reb":null,"ast":null,"stl":null,"blk":null,"tov":null,"fgm":null,"fga":null,"tpm":null,"tpa":null,"ftm":null,"fta":null,"pm":null,"start":false},{"pid":"bouknja01","name":"James Bouknight","min":null,"pts":null,"reb":null,"ast":null,"stl":null,"blk":null,"tov":null,"fgm":null,"fga":null,"tpm":null,"tpa":null,"ftm":null,"fta":null,"pm":null,"start":false},{"pid":"ballla01","name":"LaMelo Ball","min":36,"pts":null,"reb":null,"ast":null,"stl":null,"blk":null,"tov":null,"fgm":null,"fga":null,"tpm":null,"tpa":null,"ftm":null,"fta":null,"pm":null,"start":true},{"pid":"maledth01","name":"Theo Maledon","min":11,"pts":null,"reb":null,"ast":null,"stl":null,"blk":null,"tov":null,"fgm":null,"fga":null,"tpm":null,"tpa":null,"ftm":null,"fta":null,"pm":null,"start":false},{"pid":"haywago01","name":"Gordon Hayward","min":36,"pts":null,"reb":null,"ast":null,"stl":null,"blk":null,"tov":null,"fgm":null,"fga":null,"tpm":null,"tpa":null,"ftm":null,"fta":null,"pm":null,"start":true},{"pid":"mcdanja01","name":"Jalen McDaniels","min":22,"pts":null,"reb":null,"ast":null,"stl":null,"blk":null,"tov":null,"fgm":null,"fga":null,"tpm":null,"tpa":null,"ftm":null,"fta":null,"pm":null,"start":false},{"pid":"plumlma01","name":"Mason Plumlee","min":26,"pts":null,"reb":null,"ast":null,"stl":null,"blk":null,"tov":null,"fgm":null,"fga":null,"tpm":null,"tpa":null,"ftm":null,"fta":null,"pm":null,"start":true}],"away":[{"pid":"manntr01","name":"Tre Mann","min":22,"pts":null,"reb":null,"ast":null,"stl":null,"blk":null,"tov":null,"fgm":null,"fga":null,"tpm":null,"tpa":null,"ftm":null,"fta":null,"pm":null,"start":false},{"pid":"willija06","name":"Jalen Williams","min":27,"pts":null,"reb":null,"ast":null,"stl":null,"blk":null,"tov":null,"fgm":null,"fga":null,"tpm":null,"tpa":null,"ftm":null,"fta":null,"pm":null,"start":true},{"pid":"muscami01","name":"Mike Muscala","min":19,"pts":null,"reb":null,"ast":null,"stl":null,"blk":null,"tov":null,"fgm":null,"fga":null,"tpm":null,"tpa":null,"ftm":null,"fta":null,"pm":null,"start":false},{"pid":"dortlu01","name":"Luguentz Dort","min":27,"pts":null,"reb":null,"ast":null,"stl":null,"blk":null,"tov":null,"fgm":null,"fga":null,"tpm":null,"tpa":null,"ftm":null,"fta":null,"pm":null,"start":true},{"pid":"omorueu01","name":"Eugene Omoruyi","min":4,"pts":null,"reb":null,"ast":null,"stl":null,"blk":null,"tov":null,"fgm":null,"fga":null,"tpm":null,"tpa":null,"ftm":null,"fta":null,"pm":null,"start":false},{"pid":"willija07","name":"Jaylin Williams","min":24,"pts":null,"reb":null,"ast":null,"stl":null,"blk":null,"tov":null,"fgm":null,"fga":null,"tpm":null,"tpa":null,"ftm":null,"fta":null,"pm":null,"start":true},{"pid":"gilgesh01","name":"Shai Gilgeous-Alexander","min":35,"pts":null,"reb":null,"ast":null,"stl":null,"blk":null,"tov":null,"fgm":null,"fga":null,"tpm":null,"tpa":null,"ftm":null,"fta":null,"pm":null,"start":true},{"pid":"wiggiaa01","name":"Aaron Wiggins","min":17,"pts":null,"reb":null,"ast":null,"stl":null,"blk":null,"tov":null,"fgm":null,"fga":null,"tpm":null,"tpa":null,"ftm":null,"fta":null,"pm":null,"start":false},{"pid":"bazleda01","name":"Darius Bazley","min":null,"pts":null,"reb":null,"ast":null,"stl":null,"blk":null,"tov":null,"fgm":null,"fga":null,"tpm":null,"tpa":null,"ftm":null,"fta":null,"pm":null,"start":false},{"pid":"willike04","name":"Kenrich Williams","min":15,"pts":null,"reb":null,"ast":null,"stl":null,"blk":null,"tov":null,"fgm":null,"fga":null,"tpm":null,"tpa":null,"ftm":null,"fta":null,"pm":null,"start":false},{"pid":"giddejo01","name":"Josh Giddey","min":33,"pts":null,"reb":null,"ast":null,"stl":null,"blk":null,"tov":null,"fgm":null,"fga":null,"tpm":null,"tpa":null,"ftm":null,"fta":null,"pm":null,"start":true},{"pid":"joeis01","name":"Isaiah Joe","min":12,"pts":null,"reb":null,"ast":null,"stl":null,"blk":null,"tov":null,"fgm":null,"fga":null,"tpm":null,"tpa":null,"ftm":null,"fta":null,"pm":null,"start":false}]}}