{"id":"24800066","date":"1948-11-27","season":1949,"type":"Regular Season","label":"","arena":"","arenaCity":"","attendance":null,"officials":"","home":{"abbr":"NYK","score":80,"q":[],"fg":0.0,"reb":0,"ast":0,"paint":0,"fast":0},"away":{"abbr":"FTW","score":70,"q":[],"fg":0.0,"reb":0,"ast":0,"paint":0,"fast":0},"box":{"home":[{"pid":null,"name":"John Palmer","min":0,"pts":16,"reb":0,"ast":0,"stl":0,"blk":0,"tov":0,"fgm":5,"fga":0,"tpm":0,"tpa":0,"ftm":6,"fta":7,"pm":0,"start":false},{"pid":"knorele01","name":"Lee Knorek","min":0,"pts":15,"reb":0,"ast":0,"stl":0,"blk":0,"tov":0,"fgm":7,"fga":0,"tpm":0,"tpa":0,"ftm":1,"fta":3,"pm":0,"start":false},{"pid":"braunca01","name":"Carl Braun","min":0,"pts":14,"reb":0,"ast":0,"stl":0,"blk":0,"tov":0,"fgm":5,"fga":0,"tpm":0,"tpa":0,"ftm":4,"fta":4,"pm":0,"start":false},{"pid":"byrneto01","name":"Tommy Byrnes","min":0,"pts":10,"reb":0,"ast":0,"stl":0,"blk":0,"tov":0,"fgm":3,"fga":0,"tpm":0,"tpa":0,"ftm":4,"fta":7,"pm":0,"start":false},{"pid":"rotheir01","name":"Irv Rothenberg","min":0,"pts":10,"reb":0,"ast":0,"stl":0,"blk":0,"tov":0,"fgm":3,"fga":0,"tpm":0,"tpa":0,"ftm":4,"fta":8,"pm":0,"start":false},{"pid":"vanbrbu01","name":"Butch Van Breda Kolff","min":0,"pts":9,"reb":0,"ast":0,"stl":0,"blk":0,"tov":0,"fgm":2,"fga":0,"tpm":0,"tpa":0,"ftm":5,"fta":12,"pm":0,"start":false},{"pid":"noelpa01","name":"Paul Noel","min":0,"pts":4,"reb":0,"ast":0,"stl":0,"blk":0,"tov":0,"fgm":1,"fga":0,"tpm":0,"tpa":0,"ftm":2,"fta":2,"pm":0,"start":false},{"pid":null,"name":"Sid Tannenbaum","min":0,"pts":2,"reb":0,"ast":0,"stl":0,"blk":0,"tov":0,"fgm":0,"fga":0,"tpm":0,"tpa":0,"ftm":2,"fta":4,"pm":0,"start":false},{"pid":"mcgahme01","name":"Mel McGaha","min":0,"pts":0,"reb":0,"ast":0,"stl":0,"blk":0,"tov":0,"fgm":0,"fga":0,"tpm":0,"tpa":0,"ftm":0,"fta":0,"pm":0,"start":false},{"pid":null,"name":"Goebel Ritter","min":0,"pts":0,"reb":0,"ast":0,"stl":0,"blk":0,"tov":0,"fgm":0,"fga":0,"tpm":0,"tpa":0,"ftm":0,"fta":0,"pm":0,"start":false},{"pid":"gallaha01","name":"Harry Gallatin","min":0,"pts":0,"reb":0,"ast":0,"stl":0,"blk":0,"tov":0,"fgm":0,"fga":0,"tpm":0,"tpa":0,"ftm":0,"fta":0,"pm":0,"start":false}],"away":[{"pid":"smileja01","name":"Jack Smiley","min":0,"pts":12,"reb":0,"ast":0,"stl":0,"blk":0,"tov":0,"fgm":5,"fga":0,"tpm":0,"tpa":0,"ftm":2,"fta":5,"pm":0,"start":false},{"pid":"pelkija01","name":"Jake Pelkington","min":0,"pts":12,"reb":0,"ast":0,"stl":0,"blk":0,"tov":0,"fgm":2,"fga":0,"tpm":0,"tpa":0,"ftm":8,"fta":9,"pm":0,"start":false},{"pid":"kinnebo01","name":"Bob Kinney","min":0,"pts":10,"reb":0,"ast":0,"stl":0,"blk":0,"tov":0,"fgm":3,"fga":0,"tpm":0,"tpa":0,"ftm":4,"fta":7,"pm":0,"start":false},{"pid":null,"name":"William Towery","min":0,"pts":9,"reb":0,"ast":0,"stl":0,"blk":0,"tov":0,"fgm":4,"fga":0,"tpm":0,"tpa":0,"ftm":1,"fta":2,"pm":0,"start":false},{"pid":"williwa01","name":"Ward Williams","min":0,"pts":6,"reb":0,"ast":0,"stl":0,"blk":0,"tov":0,"fgm":2,"fga":0,"tpm":0,"tpa":0,"ftm":2,"fta":2,"pm":0,"start":false},{"pid":"triptdi01","name":"Dick Triptow","min":0,"pts":6,"reb":0,"ast":0,"stl":0,"blk":0,"tov":0,"fgm":3,"fga":0,"tpm":0,"tpa":0,"ftm":0,"fta":0,"pm":0,"start":false},{"pid":"toughbo01","name":"Bob Tough","min":0,"pts":6,"reb":0,"ast":0,"stl":0,"blk":0,"tov":0,"fgm":3,"fga":0,"tpm":0,"tpa":0,"ftm":0,"fta":0,"pm":0,"start":false},{"pid":null,"name":"Paul Armstrong","min":0,"pts":4,"reb":0,"ast":0,"stl":0,"blk":0,"tov":0,"fgm":1,"fga":0,"tpm":0,"tpa":0,"ftm":2,"fta":3,"pm":0,"start":false},{"pid":"kirkwa01","name":"Walt Kirk","min":0,"pts":4,"reb":0,"ast":0,"stl":0,"blk":0,"tov":0,"fgm":2,"fga":0,"tpm":0,"tpa":0,"ftm":0,"fta":1,"pm":0,"start":false},{"pid":null,"name":"John Niemiera","min":0,"pts":1,"reb":0,"ast":0,"stl":0,"blk":0,"tov":0,"fgm":0,"fga":0,"tpm":0,"tpa":0,"ftm":1,"fta":1,"pm":0,"start":false},{"pid":"crockdi01","name":"Dillard Crocker","min":0,"pts":0,"reb":0,"ast":0,"stl":0,"blk":0,"tov":0,"fgm":0,"fga":0,"tpm":0,"tpa":0,"ftm":0,"fta":0,"pm":0,"start":false}]}}