{"id":"27000535","date":"1971-02-14","season":1971,"type":"Regular Season","label":"","arena":"","arenaCity":"","attendance":null,"officials":"","home":{"abbr":"DET","score":108,"q":[21,33,29,25],"fg":0.0,"reb":0,"ast":0,"paint":0,"fast":0},"away":{"abbr":"BOS","score":110,"q":[29,23,27,31],"fg":0.0,"reb":0,"ast":0,"paint":0,"fast":0},"box":{"home":[{"pid":"bingda01","name":"Dave Bing","min":45,"pts":27,"reb":5,"ast":4,"stl":0,"blk":0,"tov":0,"fgm":12,"fga":24,"tpm":0,"tpa":0,"ftm":3,"fta":4,"pm":0,"start":false},{"pid":"dischte01","name":"Terry Dischinger","min":36,"pts":17,"reb":7,"ast":2,"stl":0,"blk":0,"tov":0,"fgm":8,"fga":12,"tpm":0,"tpa":0,"ftm":1,"fta":5,"pm":0,"start":false},{"pid":"hewitbi01","name":"Bill Hewitt","min":43,"pts":15,"reb":15,"ast":3,"stl":0,"blk":0,"tov":0,"fgm":7,"fga":13,"tpm":0,"tpa":0,"ftm":1,"fta":2,"pm":0,"start":false},{"pid":"walkeji01","name":"Jimmy Walker","min":33,"pts":15,"reb":2,"ast":5,"stl":0,"blk":0,"tov":0,"fgm":4,"fga":13,"tpm":0,"tpa":0,"ftm":7,"fta":7,"pm":0,"start":false},{"pid":"laniebo01","name":"Bob Lanier","min":25,"pts":14,"reb":7,"ast":5,"stl":0,"blk":0,"tov":0,"fgm":4,"fga":8,"tpm":0,"tpa":0,"ftm":6,"fta":7,"pm":0,"start":false},{"pid":"mooreot01","name":"Otto Moore","min":23,"pts":11,"reb":4,"ast":1,"stl":0,"blk":0,"tov":0,"fgm":4,"fga":10,"tpm":0,"tpa":0,"ftm":3,"fta":4,"pm":0,"start":false},{"pid":"komivho01","name":"Howard Komives","min":19,"pts":5,"reb":2,"ast":3,"stl":0,"blk":0,"tov":0,"fgm":1,"fga":6,"tpm":0,"tpa":0,"ftm":3,"fta":4,"pm":0,"start":false},{"pid":"driscte01","name":"Terry Driscoll","min":14,"pts":4,"reb":4,"ast":1,"stl":0,"blk":0,"tov":0,"fgm":2,"fga":2,"tpm":0,"tpa":0,"ftm":0,"fta":0,"pm":0,"start":false}],"away":[{"pid":"havlijo01","name":"John Havlicek","min":48,"pts":36,"reb":7,"ast":13,"stl":0,"blk":0,"tov":0,"fgm":12,"fga":32,"tpm":0,"tpa":0,"ftm":12,"fta":13,"pm":0,"start":false},{"pid":"cowenda01","name":"Dave Cowens","min":32,"pts":18,"reb":12,"ast":2,"stl":0,"blk":0,"tov":0,"fgm":8,"fga":21,"tpm":0,"tpa":0,"ftm":2,"fta":2,"pm":0,"start":false},{"pid":"nelsodo01","name":"Don Nelson","min":32,"pts":18,"reb":6,"ast":1,"stl":0,"blk":0,"tov":0,"fgm":7,"fga":10,"tpm":0,"tpa":0,"ftm":4,"fta":6,"pm":0,"start":false},{"pid":"chanedo01","name":"Don Chaney","min":43,"pts":13,"reb":8,"ast":3,"stl":0,"blk":0,"tov":0,"fgm":6,"fga":10,"tpm":0,"tpa":0,"ftm":1,"fta":4,"pm":0,"start":false},{"pid":"finkeha01","name":"Hank Finkel","min":29,"pts":10,"reb":7,"ast":6,"stl":0,"blk":0,"tov":0,"fgm":4,"fga":13,"tpm":0,"tpa":0,"ftm":2,"fta":2,"pm":0,"start":false},{"pid":"dinwibi01","name":"Bill Dinwiddie","min":28,"pts":9,"reb":2,"ast":1,"stl":0,"blk":0,"tov":0,"fgm":4,"fga":7,"tpm":0,"tpa":0,"ftm":1,"fta":2,"pm":0,"start":false},{"pid":"kuberst01","name":"Steve Kuberski","min":23,"pts":6,"reb":7,"ast":1,"stl":0,"blk":0,"tov":0,"fgm":2,"fga":5,"tpm":0,"tpa":0,"ftm":2,"fta":2,"pm":0,"start":false},{"pid":null,"name":"Arthur Williams","min":5,"pts":0,"reb":0,"ast":1,"stl":0,"blk":0,"tov":0,"fgm":0,"fga":0,"tpm":0,"tpa":0,"ftm":0,"fta":0,"pm":0,"start":false}]}}