{"id":"28100217","date":"1981-12-09","season":1982,"type":"Regular Season","label":"","arena":"","arenaCity":"","attendance":null,"officials":"","home":{"abbr":"CLE","score":112,"q":[23,21,23,29,16],"fg":0.0,"reb":0,"ast":0,"paint":0,"fast":0},"away":{"abbr":"ATL","score":108,"q":[29,21,22,24,12],"fg":0.0,"reb":0,"ast":0,"paint":0,"fast":0},"box":{"home":[{"pid":"mitchmi01","name":"Mike Mitchell","min":47,"pts":27,"reb":3,"ast":6,"stl":0,"blk":1,"tov":0,"fgm":11,"fga":26,"tpm":0,"tpa":0,"ftm":5,"fta":8,"pm":0,"start":false},{"pid":"edwarja01","name":"James Edwards","min":39,"pts":23,"reb":10,"ast":5,"stl":0,"blk":2,"tov":0,"fgm":8,"fga":11,"tpm":0,"tpa":0,"ftm":7,"fta":11,"pm":0,"start":false},{"pid":"pheglro01","name":"Roger Phegley","min":36,"pts":17,"reb":3,"ast":6,"stl":0,"blk":0,"tov":0,"fgm":7,"fga":14,"tpm":1,"tpa":1,"ftm":2,"fta":2,"pm":0,"start":false},{"pid":"washiri01","name":"Richard Washington","min":23,"pts":12,"reb":4,"ast":1,"stl":0,"blk":0,"tov":0,"fgm":6,"fga":13,"tpm":0,"tpa":0,"ftm":0,"fta":0,"pm":0,"start":false},{"pid":"carrke01","name":"Kenny Carr","min":31,"pts":12,"reb":8,"ast":1,"stl":0,"blk":0,"tov":0,"fgm":5,"fga":8,"tpm":0,"tpa":0,"ftm":2,"fta":5,"pm":0,"start":false},{"pid":"hustoge01","name":"Geoff Huston","min":41,"pts":8,"reb":5,"ast":7,"stl":0,"blk":0,"tov":0,"fgm":4,"fga":7,"tpm":0,"tpa":0,"ftm":0,"fta":2,"pm":0,"start":false},{"pid":"laimbbi01","name":"Bill Laimbeer","min":13,"pts":7,"reb":4,"ast":1,"stl":0,"blk":0,"tov":0,"fgm":3,"fga":5,"tpm":0,"tpa":0,"ftm":1,"fta":2,"pm":0,"start":false},{"pid":"silasja01","name":"James Silas","min":28,"pts":6,"reb":1,"ast":6,"stl":0,"blk":0,"tov":0,"fgm":0,"fga":4,"tpm":0,"tpa":0,"ftm":6,"fta":6,"pm":0,"start":false},{"pid":"forddo01","name":"Don Ford","min":4,"pts":0,"reb":0,"ast":0,"stl":0,"blk":0,"tov":0,"fgm":0,"fga":0,"tpm":0,"tpa":0,"ftm":0,"fta":0,"pm":0,"start":false},{"pid":"dillami01","name":"Mickey Dillard","min":3,"pts":0,"reb":0,"ast":0,"stl":0,"blk":0,"tov":0,"fgm":0,"fga":1,"tpm":0,"tpa":0,"ftm":0,"fta":0,"pm":0,"start":false}],"away":[{"pid":"roundda01","name":"Dan Roundfield","min":46,"pts":33,"reb":12,"ast":1,"stl":0,"blk":1,"tov":0,"fgm":12,"fga":20,"tpm":0,"tpa":0,"ftm":9,"fta":13,"pm":0,"start":false},{"pid":"mcmilto01","name":"Tom McMillen","min":32,"pts":22,"reb":4,"ast":2,"stl":0,"blk":0,"tov":0,"fgm":8,"fga":13,"tpm":0,"tpa":0,"ftm":6,"fta":8,"pm":0,"start":false},{"pid":"hawesst01","name":"Steve Hawes","min":35,"pts":17,"reb":8,"ast":3,"stl":0,"blk":0,"tov":0,"fgm":7,"fga":11,"tpm":1,"tpa":1,"ftm":2,"fta":2,"pm":0,"start":false},{"pid":"sparrro01","name":"Rory Sparrow","min":39,"pts":14,"reb":3,"ast":6,"stl":0,"blk":0,"tov":0,"fgm":6,"fga":9,"tpm":0,"tpa":0,"ftm":2,"fta":2,"pm":0,"start":false},{"pid":null,"name":"Eddie Johnson","min":40,"pts":12,"reb":2,"ast":6,"stl":0,"blk":0,"tov":0,"fgm":4,"fga":12,"tpm":0,"tpa":0,"ftm":4,"fta":8,"pm":0,"start":false},{"pid":"crissch01","name":"Charlie Criss","min":14,"pts":4,"reb":3,"ast":0,"stl":0,"blk":0,"tov":0,"fgm":1,"fga":2,"tpm":0,"tpa":0,"ftm":2,"fta":2,"pm":0,"start":false},{"pid":"drewjo01","name":"John Drew","min":15,"pts":4,"reb":0,"ast":0,"stl":0,"blk":0,"tov":0,"fgm":2,"fga":5,"tpm":0,"tpa":0,"ftm":0,"fta":0,"pm":0,"start":false},{"pid":"rollitr01","name":"Tree Rollins","min":18,"pts":1,"reb":6,"ast":0,"stl":0,"blk":0,"tov":0,"fgm":0,"fga":2,"tpm":0,"tpa":0,"ftm":1,"fta":2,"pm":0,"start":false},{"pid":"macklru01","name":"Rudy Macklin","min":13,"pts":1,"reb":1,"ast":0,"stl":0,"blk":0,"tov":0,"fgm":0,"fga":3,"tpm":0,"tpa":0,"ftm":1,"fta":2,"pm":0,"start":false},{"pid":"mcelrji01","name":"Jim McElroy","min":13,"pts":0,"reb":0,"ast":1,"stl":0,"blk":0,"tov":0,"fgm":0,"fga":1,"tpm":0,"tpa":0,"ftm":0,"fta":0,"pm":0,"start":false}]}}