{"id":"28100624","date":"1982-02-24","season":1982,"type":"Regular Season","label":"","arena":"","arenaCity":"","attendance":null,"officials":"","home":{"abbr":"DEN","score":110,"q":[29,26,36,19],"fg":0.457,"reb":51,"ast":0,"paint":0,"fast":0},"away":{"abbr":"HOU","score":120,"q":[27,38,31,24],"fg":0.543,"reb":40,"ast":0,"paint":0,"fast":0},"box":{"home":[{"pid":"vandeki01","name":"Kiki Vandeweghe","min":41,"pts":34,"reb":11,"ast":3,"stl":0,"blk":0,"tov":1,"fgm":15,"fga":24,"tpm":0,"tpa":1,"ftm":4,"fta":5,"pm":0,"start":false},{"pid":"isselda01","name":"Dan Issel","min":41,"pts":24,"reb":13,"ast":0,"stl":0,"blk":2,"tov":3,"fgm":9,"fga":17,"tpm":0,"tpa":1,"ftm":6,"fta":6,"pm":0,"start":false},{"pid":"dunntr01","name":"T.R. Dunn","min":36,"pts":13,"reb":10,"ast":3,"stl":2,"blk":1,"tov":2,"fgm":6,"fga":12,"tpm":0,"tpa":0,"ftm":1,"fta":4,"pm":0,"start":false},{"pid":"mckinbi01","name":"Billy McKinney","min":19,"pts":11,"reb":1,"ast":4,"stl":1,"blk":0,"tov":1,"fgm":4,"fga":7,"tpm":0,"tpa":0,"ftm":3,"fta":3,"pm":0,"start":false},{"pid":"englial01","name":"Alex English","min":28,"pts":10,"reb":1,"ast":3,"stl":0,"blk":1,"tov":4,"fgm":4,"fga":7,"tpm":0,"tpa":0,"ftm":2,"fta":2,"pm":0,"start":false},{"pid":"gondrgl01","name":"Glen Gondrezick","min":27,"pts":8,"reb":9,"ast":2,"stl":4,"blk":0,"tov":2,"fgm":2,"fga":8,"tpm":0,"tpa":0,"ftm":4,"fta":4,"pm":0,"start":false},{"pid":"thompda01","name":"David Thompson","min":23,"pts":8,"reb":2,"ast":6,"stl":0,"blk":1,"tov":5,"fgm":2,"fga":11,"tpm":0,"tpa":1,"ftm":4,"fta":6,"pm":0,"start":false},{"pid":"higgske01","name":"Kenny Higgs","min":14,"pts":2,"reb":3,"ast":2,"stl":0,"blk":0,"tov":2,"fgm":1,"fga":4,"tpm":0,"tpa":0,"ftm":0,"fta":0,"pm":0,"start":false},{"pid":"rochejo01","name":"John Roche","min":4,"pts":0,"reb":0,"ast":1,"stl":0,"blk":0,"tov":0,"fgm":0,"fga":2,"tpm":0,"tpa":2,"ftm":0,"fta":0,"pm":0,"start":false},{"pid":"hordgce01","name":"Cedrick Hordges","min":7,"pts":0,"reb":1,"ast":1,"stl":0,"blk":1,"tov":2,"fgm":0,"fga":2,"tpm":0,"tpa":0,"ftm":0,"fta":0,"pm":0,"start":false}],"away":[{"pid":"leaveal01","name":"Allen Leavell","min":36,"pts":32,"reb":4,"ast":9,"stl":6,"blk":0,"tov":4,"fgm":15,"fga":21,"tpm":1,"tpa":2,"ftm":1,"fta":1,"pm":0,"start":false},{"pid":"hayesel01","name":"Elvin Hayes","min":42,"pts":27,"reb":8,"ast":3,"stl":0,"blk":5,"tov":1,"fgm":11,"fga":16,"tpm":0,"tpa":0,"ftm":5,"fta":8,"pm":0,"start":false},{"pid":"malonmo01","name":"Moses Malone","min":45,"pts":23,"reb":9,"ast":2,"stl":0,"blk":1,"tov":4,"fgm":8,"fga":17,"tpm":0,"tpa":1,"ftm":7,"fta":8,"pm":0,"start":false},{"pid":"reidro01","name":"Robert Reid","min":44,"pts":17,"reb":11,"ast":6,"stl":1,"blk":1,"tov":2,"fgm":7,"fga":15,"tpm":0,"tpa":1,"ftm":3,"fta":4,"pm":0,"start":false},{"pid":"hendeto01","name":"Tom Henderson","min":27,"pts":6,"reb":1,"ast":7,"stl":3,"blk":0,"tov":1,"fgm":3,"fga":8,"tpm":0,"tpa":0,"ftm":0,"fta":0,"pm":0,"start":false},{"pid":"murphca01","name":"Calvin Murphy","min":16,"pts":6,"reb":0,"ast":1,"stl":0,"blk":0,"tov":3,"fgm":2,"fga":8,"tpm":0,"tpa":0,"ftm":2,"fta":2,"pm":0,"start":false},{"pid":"jonesma01","name":"Major Jones","min":13,"pts":5,"reb":3,"ast":2,"stl":1,"blk":1,"tov":2,"fgm":2,"fga":2,"tpm":0,"tpa":0,"ftm":1,"fta":2,"pm":0,"start":false},{"pid":null,"name":"Mike Dunleavy","min":17,"pts":4,"reb":4,"ast":3,"stl":0,"blk":0,"tov":1,"fgm":2,"fga":5,"tpm":0,"tpa":0,"ftm":0,"fta":0,"pm":0,"start":false}]}}