{"id":"28200816","date":"1983-03-27","season":1983,"type":"Regular Season","label":"","arena":"","arenaCity":"","attendance":null,"officials":"","home":{"abbr":"PHI","score":94,"q":[24,24,22,24],"fg":0.493,"reb":42,"ast":16,"paint":0,"fast":0},"away":{"abbr":"CLE","score":80,"q":[19,18,24,19],"fg":0.376,"reb":46,"ast":17,"paint":0,"fast":0},"box":{"home":[{"pid":"curetea01","name":"Earl Cureton","min":25,"pts":null,"reb":null,"ast":null,"stl":null,"blk":null,"tov":null,"fgm":null,"fga":null,"tpm":null,"tpa":null,"ftm":null,"fta":null,"pm":null,"start":false},{"pid":"malonmo01","name":"Moses Malone","min":37,"pts":null,"reb":null,"ast":null,"stl":null,"blk":null,"tov":null,"fgm":null,"fga":null,"tpm":null,"tpa":null,"ftm":null,"fta":null,"pm":null,"start":false},{"pid":null,"name":"Bobby Jones","min":27,"pts":null,"reb":null,"ast":null,"stl":null,"blk":null,"tov":null,"fgm":null,"fga":null,"tpm":null,"tpa":null,"ftm":null,"fta":null,"pm":null,"start":false},{"pid":"johnsre01","name":"Reggie Johnson","min":26,"pts":null,"reb":null,"ast":null,"stl":null,"blk":null,"tov":null,"fgm":null,"fga":null,"tpm":null,"tpa":null,"ftm":null,"fta":null,"pm":null,"start":false},{"pid":"edwarfr01","name":"Franklin Edwards","min":21,"pts":null,"reb":null,"ast":null,"stl":null,"blk":null,"tov":null,"fgm":null,"fga":null,"tpm":null,"tpa":null,"ftm":null,"fta":null,"pm":null,"start":false},{"pid":"cheekma01","name":"Maurice Cheeks","min":27,"pts":null,"reb":null,"ast":null,"stl":null,"blk":null,"tov":null,"fgm":null,"fga":null,"tpm":null,"tpa":null,"ftm":null,"fta":null,"pm":null,"start":false},{"pid":"johnscl01","name":"Clemon Johnson","min":29,"pts":null,"reb":null,"ast":null,"stl":null,"blk":null,"tov":null,"fgm":null,"fga":null,"tpm":null,"tpa":null,"ftm":null,"fta":null,"pm":null,"start":false},{"pid":"richacl01","name":"Clint Richardson","min":20,"pts":null,"reb":null,"ast":null,"stl":null,"blk":null,"tov":null,"fgm":null,"fga":null,"tpm":null,"tpa":null,"ftm":null,"fta":null,"pm":null,"start":false},{"pid":"toneyan01","name":"Andrew Toney","min":28,"pts":null,"reb":null,"ast":null,"stl":null,"blk":null,"tov":null,"fgm":null,"fga":null,"tpm":null,"tpa":null,"ftm":null,"fta":null,"pm":null,"start":false}],"away":[{"pid":"wilkebo01","name":"Bob Wilkerson","min":25,"pts":null,"reb":null,"ast":null,"stl":null,"blk":null,"tov":null,"fgm":null,"fga":null,"tpm":null,"tpa":null,"ftm":null,"fta":null,"pm":null,"start":false},{"pid":"flowebr01","name":"Bruce Flowers","min":7,"pts":null,"reb":null,"ast":null,"stl":null,"blk":null,"tov":null,"fgm":null,"fga":null,"tpm":null,"tpa":null,"ftm":null,"fta":null,"pm":null,"start":false},{"pid":null,"name":"World Free","min":38,"pts":null,"reb":null,"ast":null,"stl":null,"blk":null,"tov":null,"fgm":null,"fga":null,"tpm":null,"tpa":null,"ftm":null,"fta":null,"pm":null,"start":false},{"pid":"hustoge01","name":"Geoff Huston","min":33,"pts":null,"reb":null,"ast":null,"stl":null,"blk":null,"tov":null,"fgm":null,"fga":null,"tpm":null,"tpa":null,"ftm":null,"fta":null,"pm":null,"start":false},{"pid":"laceysa01","name":"Sam Lacey","min":16,"pts":null,"reb":null,"ast":null,"stl":null,"blk":null,"tov":null,"fgm":null,"fga":null,"tpm":null,"tpa":null,"ftm":null,"fta":null,"pm":null,"start":false},{"pid":"hayesst01","name":"Steve Hayes","min":18,"pts":null,"reb":null,"ast":null,"stl":null,"blk":null,"tov":null,"fgm":null,"fga":null,"tpm":null,"tpa":null,"ftm":null,"fta":null,"pm":null,"start":false},{"pid":"hubbaph01","name":"Phil Hubbard","min":30,"pts":null,"reb":null,"ast":null,"stl":null,"blk":null,"tov":null,"fgm":null,"fga":null,"tpm":null,"tpa":null,"ftm":null,"fta":null,"pm":null,"start":false},{"pid":null,"name":"Cliff T. Robinson","min":34,"pts":null,"reb":null,"ast":null,"stl":null,"blk":null,"tov":null,"fgm":null,"fga":null,"tpm":null,"tpa":null,"ftm":null,"fta":null,"pm":null,"start":false},{"pid":"tillida01","name":"Darren Tillis","min":25,"pts":null,"reb":null,"ast":null,"stl":null,"blk":null,"tov":null,"fgm":null,"fga":null,"tpm":null,"tpa":null,"ftm":null,"fta":null,"pm":null,"start":false},{"pid":"cookje01","name":"Jeff Cook","min":14,"pts":null,"reb":null,"ast":null,"stl":null,"blk":null,"tov":null,"fgm":null,"fga":null,"tpm":null,"tpa":null,"ftm":null,"fta":null,"pm":null,"start":false}]}}