{"id":"28700913","date":"1988-04-20","season":1988,"type":"Regular Season","label":"","arena":"","arenaCity":"","attendance":null,"officials":"","home":{"abbr":"DAL","score":107,"q":[27,20,30,30],"fg":0.43,"reb":35,"ast":23,"paint":0,"fast":0},"away":{"abbr":"LAL","score":114,"q":[27,31,33,23],"fg":0.587,"reb":43,"ast":37,"paint":0,"fast":0},"box":{"home":[{"pid":"davisbr01","name":"Brad Davis","min":11,"pts":null,"reb":null,"ast":null,"stl":null,"blk":null,"tov":null,"fgm":null,"fga":null,"tpm":null,"tpa":null,"ftm":null,"fta":null,"pm":null,"start":false},{"pid":"aguirma01","name":"Mark Aguirre","min":34,"pts":null,"reb":null,"ast":null,"stl":null,"blk":null,"tov":null,"fgm":null,"fga":null,"tpm":null,"tpa":null,"ftm":null,"fta":null,"pm":null,"start":false},{"pid":"schrede01","name":"Detlef Schrempf","min":18,"pts":null,"reb":null,"ast":null,"stl":null,"blk":null,"tov":null,"fgm":null,"fga":null,"tpm":null,"tpa":null,"ftm":null,"fta":null,"pm":null,"start":false},{"pid":"harpede01","name":"Derek Harper","min":39,"pts":null,"reb":null,"ast":null,"stl":null,"blk":null,"tov":null,"fgm":null,"fga":null,"tpm":null,"tpa":null,"ftm":null,"fta":null,"pm":null,"start":false},{"pid":"perkisa01","name":"Sam Perkins","min":40,"pts":null,"reb":null,"ast":null,"stl":null,"blk":null,"tov":null,"fgm":null,"fga":null,"tpm":null,"tpa":null,"ftm":null,"fta":null,"pm":null,"start":false},{"pid":"blackro01","name":"Rolando Blackman","min":45,"pts":null,"reb":null,"ast":null,"stl":null,"blk":null,"tov":null,"fgm":null,"fga":null,"tpm":null,"tpa":null,"ftm":null,"fta":null,"pm":null,"start":false},{"pid":"tarplro01","name":"Roy Tarpley","min":29,"pts":null,"reb":null,"ast":null,"stl":null,"blk":null,"tov":null,"fgm":null,"fga":null,"tpm":null,"tpa":null,"ftm":null,"fta":null,"pm":null,"start":false},{"pid":"donalja01","name":"James Donaldson","min":24,"pts":null,"reb":null,"ast":null,"stl":null,"blk":null,"tov":null,"fgm":null,"fga":null,"tpm":null,"tpa":null,"ftm":null,"fta":null,"pm":null,"start":false}],"away":[{"pid":"coopemi01","name":"Michael Cooper","min":37,"pts":null,"reb":null,"ast":null,"stl":null,"blk":null,"tov":null,"fgm":null,"fga":null,"tpm":null,"tpa":null,"ftm":null,"fta":null,"pm":null,"start":false},{"pid":"campbto01","name":"Tony Campbell","min":15,"pts":null,"reb":null,"ast":null,"stl":null,"blk":null,"tov":null,"fgm":null,"fga":null,"tpm":null,"tpa":null,"ftm":null,"fta":null,"pm":null,"start":false},{"pid":"johnsma02","name":"Magic Johnson","min":42,"pts":null,"reb":null,"ast":null,"stl":null,"blk":null,"tov":null,"fgm":null,"fga":null,"tpm":null,"tpa":null,"ftm":null,"fta":null,"pm":null,"start":false},{"pid":"thompmy01","name":"Mychal Thompson","min":29,"pts":null,"reb":null,"ast":null,"stl":null,"blk":null,"tov":null,"fgm":null,"fga":null,"tpm":null,"tpa":null,"ftm":null,"fta":null,"pm":null,"start":false},{"pid":"greenac01","name":"A.C. Green","min":21,"pts":null,"reb":null,"ast":null,"stl":null,"blk":null,"tov":null,"fgm":null,"fga":null,"tpm":null,"tpa":null,"ftm":null,"fta":null,"pm":null,"start":false},{"pid":"rambiku01","name":"Kurt Rambis","min":21,"pts":null,"reb":null,"ast":null,"stl":null,"blk":null,"tov":null,"fgm":null,"fga":null,"tpm":null,"tpa":null,"ftm":null,"fta":null,"pm":null,"start":false},{"pid":"scottby01","name":"Byron Scott","min":46,"pts":null,"reb":null,"ast":null,"stl":null,"blk":null,"tov":null,"fgm":null,"fga":null,"tpm":null,"tpa":null,"ftm":null,"fta":null,"pm":null,"start":false},{"pid":"abdulka01","name":"Kareem Abdul-Jabbar","min":29,"pts":null,"reb":null,"ast":null,"stl":null,"blk":null,"tov":null,"fgm":null,"fga":null,"tpm":null,"tpa":null,"ftm":null,"fta":null,"pm":null,"start":false}]}}