{"id":"29001032","date":"1991-04-11","season":1991,"type":"Regular Season","label":"","arena":"","arenaCity":"","attendance":null,"officials":"","home":{"abbr":"SAC","score":104,"q":[24,24,33,23],"fg":0.449,"reb":44,"ast":25,"paint":0,"fast":0},"away":{"abbr":"ORL","score":96,"q":[23,26,28,19],"fg":0.449,"reb":44,"ast":20,"paint":0,"fast":0},"box":{"home":[{"pid":"wennibi01","name":"Bill Wennington","min":19,"pts":null,"reb":null,"ast":null,"stl":null,"blk":null,"tov":null,"fgm":null,"fga":null,"tpm":null,"tpa":null,"ftm":null,"fta":null,"pm":null,"start":false},{"pid":"sparrro01","name":"Rory Sparrow","min":33,"pts":null,"reb":null,"ast":null,"stl":null,"blk":null,"tov":null,"fgm":null,"fga":null,"tpm":null,"tpa":null,"ftm":null,"fta":null,"pm":null,"start":false},{"pid":"lesji01","name":"Jim Les","min":28,"pts":null,"reb":null,"ast":null,"stl":null,"blk":null,"tov":null,"fgm":null,"fga":null,"tpm":null,"tpa":null,"ftm":null,"fta":null,"pm":null,"start":false},{"pid":"bonnean01","name":"Anthony Bonner","min":5,"pts":null,"reb":null,"ast":null,"stl":null,"blk":null,"tov":null,"fgm":null,"fga":null,"tpm":null,"tpa":null,"ftm":null,"fta":null,"pm":null,"start":false},{"pid":"maystr01","name":"Travis Mays","min":35,"pts":null,"reb":null,"ast":null,"stl":null,"blk":null,"tov":null,"fgm":null,"fga":null,"tpm":null,"tpa":null,"ftm":null,"fta":null,"pm":null,"start":false},{"pid":"carran01","name":"Antoine Carr","min":31,"pts":null,"reb":null,"ast":null,"stl":null,"blk":null,"tov":null,"fgm":null,"fga":null,"tpm":null,"tpa":null,"ftm":null,"fta":null,"pm":null,"start":false},{"pid":"fredean01","name":"Anthony Frederick","min":12,"pts":null,"reb":null,"ast":null,"stl":null,"blk":null,"tov":null,"fgm":null,"fga":null,"tpm":null,"tpa":null,"ftm":null,"fta":null,"pm":null,"start":false},{"pid":"causwdu01","name":"Duane Causwell","min":39,"pts":null,"reb":null,"ast":null,"stl":null,"blk":null,"tov":null,"fgm":null,"fga":null,"tpm":null,"tpa":null,"ftm":null,"fta":null,"pm":null,"start":false},{"pid":"simmoli01","name":"Lionel Simmons","min":38,"pts":null,"reb":null,"ast":null,"stl":null,"blk":null,"tov":null,"fgm":null,"fga":null,"tpm":null,"tpa":null,"ftm":null,"fta":null,"pm":null,"start":false}],"away":[{"pid":"skilesc01","name":"Scott Skiles","min":41,"pts":null,"reb":null,"ast":null,"stl":null,"blk":null,"tov":null,"fgm":null,"fga":null,"tpm":null,"tpa":null,"ftm":null,"fta":null,"pm":null,"start":false},{"pid":"reynoje01","name":"Jerry Reynolds","min":26,"pts":null,"reb":null,"ast":null,"stl":null,"blk":null,"tov":null,"fgm":null,"fga":null,"tpm":null,"tpa":null,"ftm":null,"fta":null,"pm":null,"start":false},{"pid":"smithot01","name":"Otis Smith","min":41,"pts":null,"reb":null,"ast":null,"stl":null,"blk":null,"tov":null,"fgm":null,"fga":null,"tpm":null,"tpa":null,"ftm":null,"fta":null,"pm":null,"start":false},{"pid":"kitegr01","name":"Greg Kite","min":15,"pts":null,"reb":null,"ast":null,"stl":null,"blk":null,"tov":null,"fgm":null,"fga":null,"tpm":null,"tpa":null,"ftm":null,"fta":null,"pm":null,"start":false},{"pid":"anslemi01","name":"Michael Ansley","min":1,"pts":null,"reb":null,"ast":null,"stl":null,"blk":null,"tov":null,"fgm":null,"fga":null,"tpm":null,"tpa":null,"ftm":null,"fta":null,"pm":null,"start":false},{"pid":"acresma01","name":"Mark Acres","min":35,"pts":null,"reb":null,"ast":null,"stl":null,"blk":null,"tov":null,"fgm":null,"fga":null,"tpm":null,"tpa":null,"ftm":null,"fta":null,"pm":null,"start":false},{"pid":"turneje01","name":"Jeff Turner","min":41,"pts":null,"reb":null,"ast":null,"stl":null,"blk":null,"tov":null,"fgm":null,"fga":null,"tpm":null,"tpa":null,"ftm":null,"fta":null,"pm":null,"start":false},{"pid":"wileymo01","name":"Morlon Wiley","min":7,"pts":null,"reb":null,"ast":null,"stl":null,"blk":null,"tov":null,"fgm":null,"fga":null,"tpm":null,"tpa":null,"ftm":null,"fta":null,"pm":null,"start":false},{"pid":"scottde01","name":"Dennis Scott","min":33,"pts":null,"reb":null,"ast":null,"stl":null,"blk":null,"tov":null,"fgm":null,"fga":null,"tpm":null,"tpa":null,"ftm":null,"fta":null,"pm":null,"start":false}]}}