{"id":"29400157","date":"1994-11-28","season":1995,"type":"Regular Season","label":"","arena":"","arenaCity":"","attendance":null,"officials":"","home":{"abbr":"SAS","score":92,"q":[26,23,21,22],"fg":0.435,"reb":40,"ast":15,"paint":0,"fast":0},"away":{"abbr":"MIN","score":88,"q":[20,20,18,30],"fg":0.458,"reb":32,"ast":21,"paint":0,"fast":0},"box":{"home":[{"pid":"robinda01","name":"David Robinson","min":42,"pts":24,"reb":10,"ast":7,"stl":2,"blk":3,"tov":3,"fgm":6,"fga":14,"tpm":0,"tpa":0,"ftm":12,"fta":15,"pm":0,"start":false},{"pid":"delnevi01","name":"Vinny Del Negro","min":36,"pts":19,"reb":4,"ast":1,"stl":0,"blk":0,"tov":0,"fgm":8,"fga":12,"tpm":0,"tpa":0,"ftm":3,"fta":4,"pm":0,"start":false},{"pid":"elliose01","name":"Sean Elliott","min":38,"pts":16,"reb":4,"ast":3,"stl":3,"blk":0,"tov":4,"fgm":5,"fga":13,"tpm":2,"tpa":4,"ftm":4,"fta":4,"pm":0,"start":false},{"pid":"johnsav01","name":"Avery Johnson","min":36,"pts":15,"reb":2,"ast":1,"stl":1,"blk":0,"tov":3,"fgm":5,"fga":8,"tpm":0,"tpa":1,"ftm":5,"fta":6,"pm":0,"start":false},{"pid":"persoch01","name":"Chuck Person","min":33,"pts":10,"reb":7,"ast":2,"stl":2,"blk":0,"tov":4,"fgm":3,"fga":8,"tpm":2,"tpa":7,"ftm":2,"fta":2,"pm":0,"start":false},{"pid":"reidjr01","name":"J.R. Reid","min":35,"pts":5,"reb":6,"ast":1,"stl":1,"blk":1,"tov":0,"fgm":2,"fga":8,"tpm":0,"tpa":0,"ftm":1,"fta":2,"pm":0,"start":false},{"pid":"malonmo01","name":"Moses Malone","min":15,"pts":3,"reb":7,"ast":0,"stl":2,"blk":0,"tov":1,"fgm":1,"fga":4,"tpm":0,"tpa":1,"ftm":1,"fta":2,"pm":0,"start":false},{"pid":"nwosuju01","name":"Julius Nwosu","min":4,"pts":0,"reb":0,"ast":0,"stl":0,"blk":1,"tov":0,"fgm":0,"fga":1,"tpm":0,"tpa":0,"ftm":0,"fta":0,"pm":0,"start":false},{"pid":"whitnch01","name":"Chris Whitney","min":1,"pts":0,"reb":0,"ast":0,"stl":0,"blk":0,"tov":0,"fgm":0,"fga":1,"tpm":0,"tpa":0,"ftm":0,"fta":0,"pm":0,"start":false}],"away":[{"pid":"rideris01","name":"Isaiah Rider","min":37,"pts":23,"reb":4,"ast":5,"stl":1,"blk":0,"tov":2,"fgm":10,"fga":13,"tpm":1,"tpa":1,"ftm":2,"fta":4,"pm":0,"start":false},{"pid":"westdo01","name":"Doug West","min":41,"pts":18,"reb":2,"ast":1,"stl":2,"blk":1,"tov":1,"fgm":8,"fga":13,"tpm":1,"tpa":3,"ftm":1,"fta":2,"pm":0,"start":false},{"pid":"rooksse01","name":"Sean Rooks","min":39,"pts":18,"reb":4,"ast":1,"stl":0,"blk":0,"tov":4,"fgm":7,"fga":9,"tpm":0,"tpa":0,"ftm":4,"fta":7,"pm":0,"start":false},{"pid":"laettch01","name":"Christian Laettner","min":40,"pts":10,"reb":13,"ast":5,"stl":0,"blk":3,"tov":5,"fgm":3,"fga":11,"tpm":0,"tpa":0,"ftm":4,"fta":5,"pm":0,"start":false},{"pid":"eisleho01","name":"Howard Eisley","min":23,"pts":8,"reb":2,"ast":3,"stl":1,"blk":1,"tov":2,"fgm":1,"fga":5,"tpm":0,"tpa":3,"ftm":6,"fta":6,"pm":0,"start":false},{"pid":"garlawi01","name":"Winston Garland","min":25,"pts":6,"reb":2,"ast":6,"stl":2,"blk":0,"tov":2,"fgm":2,"fga":7,"tpm":0,"tpa":2,"ftm":2,"fta":2,"pm":0,"start":false},{"pid":"marshdo01","name":"Donyell Marshall","min":17,"pts":5,"reb":1,"ast":0,"stl":2,"blk":0,"tov":0,"fgm":2,"fga":7,"tpm":0,"tpa":1,"ftm":1,"fta":5,"pm":0,"start":false},{"pid":"smithch05","name":"Chris Smith","min":2,"pts":0,"reb":1,"ast":0,"stl":0,"blk":0,"tov":0,"fgm":0,"fga":0,"tpm":0,"tpa":0,"ftm":0,"fta":0,"pm":0,"start":false},{"pid":"durhapa01","name":"Pat Durham","min":1,"pts":0,"reb":0,"ast":0,"stl":0,"blk":0,"tov":0,"fgm":0,"fga":0,"tpm":0,"tpa":0,"ftm":0,"fta":0,"pm":0,"start":false},{"pid":"kingst01","name":"Stacey King","min":15,"pts":0,"reb":3,"ast":0,"stl":1,"blk":1,"tov":2,"fgm":0,"fga":7,"tpm":0,"tpa":0,"ftm":0,"fta":0,"pm":0,"start":false}]}}